cloud/__init__.py
cloud/factory.py
cloud/protocols.py
cloud/amazon/__init__.py
cloud/amazon/helpers.py
cloud/amazon/s3.py
cloud/amazon/sns.py
cloud/amazon/sqs.py
cloud/google/__init__.py
cloud/google/pubsub.py
cloud/google/storage.py
cloudtoolbox-0.5.0.dist-info/LICENSE
cloudtoolbox-0.5.0.dist-info/METADATA
cloudtoolbox-0.5.0.dist-info/WHEEL
cloudtoolbox-0.5.0.dist-info/top_level.txt
cloudtoolbox-0.5.0.dist-info/RECORD
