Metadata-Version: 2.1
Name: cloudtoolbox
Version: 0.5.0
Summary: Toolbox for the cloud.
Author-email: Dotz Developers <devs-dotz@dotz.com>
Project-URL: Repository, https://github.com/DotzInc/cloud-toolbox
Keywords: cloud,tools,utilities,google,gcp,amazon,aws
Classifier: Operating System :: OS Independent
Classifier: Programming Language :: Python :: 3 :: Only
Classifier: Programming Language :: Python :: 3.8
Classifier: Programming Language :: Python :: 3.9
Classifier: Programming Language :: Python :: 3.10
Classifier: Programming Language :: Python :: 3.11
Classifier: Programming Language :: Python :: 3.12
Classifier: Topic :: Internet
Classifier: Topic :: Software Development
Classifier: Intended Audience :: Developers
Classifier: License :: OSI Approved :: MIT License
Requires-Python: >=3.8
License-File: LICENSE
Provides-Extra: all
Requires-Dist: boto3 ; extra == 'all'
Requires-Dist: google-cloud-pubsub ; extra == 'all'
Requires-Dist: google-cloud-storage ; extra == 'all'
Provides-Extra: amazon
Requires-Dist: boto3 ; extra == 'amazon'
Provides-Extra: google
Requires-Dist: google-cloud-pubsub ; extra == 'google'
Requires-Dist: google-cloud-storage ; extra == 'google'
